rentogether/__init__.py
rentogether/__main__.py
rentogether/app.py
RenTogether-0.1.3.dist-info/LICENSE
RenTogether-0.1.3.dist-info/METADATA
RenTogether-0.1.3.dist-info/WHEEL
RenTogether-0.1.3.dist-info/entry_points.txt
RenTogether-0.1.3.dist-info/top_level.txt
RenTogether-0.1.3.dist-info/RECORD
