Metadata-Version: 2.1
Name: RenTogether
Version: 0.1.3
Summary: A Utility that Allows everyone to play VNs Together!
Home-page: https://github.com/vproHacks/RenTogether
Author: Vraj Prajapati
Author-email: vrajip@gmail.com
License: UNKNOWN
Platform: UNKNOWN
Classifier: Programming Language :: Python :: 3
Classifier: License :: OSI Approved :: MIT License
Classifier: Operating System :: OS Independent
Requires-Python: >=3.6
Requires-Dist: pygetwindow
Requires-Dist: requests
Requires-Dist: keyboard
Requires-Dist: pyscreenshot
Requires-Dist: pyautogui
Requires-Dist: pillow
